multiclass_interface/__init__.py
multiclass_interface/mpi_interface.py
multiclass_interface/multi_object_list.py
multiclass_interface/multiprocess_interface.py
multiclass_interface/version.py
multiclass_interface/tests/__init__.py
multiclass_interface/tests/my_test_cls.py
multiclass_interface/tests/test_mpi.py
multiclass_interface/tests/test_multiclass_list.py
multiclass_interface/tests/test_multiprocessinterface.py
multiclass_interface-1.17.dist-info/licenses/LICENSE
multiclass_interface-1.17.dist-info/METADATA
multiclass_interface-1.17.dist-info/WHEEL
multiclass_interface-1.17.dist-info/top_level.txt
multiclass_interface-1.17.dist-info/RECORD
