Metadata-Version: 2.4
Name: Multiclass_interface
Version: 1.17
Summary: Multiclass interface
Author-email: "Mads M. Pedersen" <mmpe@dtu.dk>
Project-URL: Homepage, https://gitlab.windenergy.dtu.dk/DYNAMIKS/multiclass_interface
Project-URL: Bug Tracker, https://gitlab.windenergy.dtu.dk/DYNAMIKS/multiclass_interface/-/issues
Classifier: Programming Language :: Python :: 3
Classifier: Operating System :: OS Independent
Classifier: License :: OSI Approved :: MIT License
Requires-Python: >=3.7
License-File: LICENSE
Requires-Dist: numpy
Provides-Extra: test
Requires-Dist: pytest; extra == "test"
Requires-Dist: pytest-cov; extra == "test"
Dynamic: license-file
